temgymbasic/__init__.py
temgymbasic/components.py
temgymbasic/functions.py
temgymbasic/gui.py
temgymbasic/model.py
temgymbasic/run.py
temgymbasic/shapes.py
temgymbasic-0.6.0.0.dist-info/METADATA
temgymbasic-0.6.0.0.dist-info/WHEEL
temgymbasic-0.6.0.0.dist-info/licenses/LICENSE.md
temgymbasic-0.6.0.0.dist-info/RECORD
